<?xml version="1.0" encoding="utf-8"?>
<CityList>
   <City X="12.4584" Y="15.3714"/>
   <City X="34.6405" Y="10.7146"/>
   <City X="31.3314" Y="23.2277"/>
   <City X="39.7545" Y="34.8178"/>
   <City X="12.5942" Y="35.5478"/>
   <City X="33.5613" Y="3.9917"/>
   <City X="12.3227" Y="31.1701"/>
   <City X="0.33065" Y="18.3816"/>
   <City X="18.6391" Y="39.0655"/>
   <City X="2.0372" Y="7.8384"/>
   <City X="31.884" Y="9.2767"/>
   <City X="5.0005" Y="21.4224"/>
   <City X="8.2884" Y="28.8952"/>
   <City X="4.1097" Y="31.0682"/>
   <City X="4.225" Y="8.7005"/>
</CityList>