<?xml version="1.0" encoding="utf-8"?>
<CityList>
   <City X="32.7773" Y="10.5858"/>
   <City X="5.3066" Y="20.4262"/>
   <City X="39.0341" Y="36.8338"/>
   <City X="16.0955" Y="10.4216"/>
   <City X="17.6332" Y="28.2379"/>
   <City X="8.5233" Y="22.8471"/>
   <City X="2.0142" Y="36.1538"/>
   <City X="21.4838" Y="31.1712"/>
   <City X="15.5583" Y="13.9613"/>
   <City X="14.9171" Y="7.1574"/>
   <City X="22.8933" Y="13.0052"/>
   <City X="27.3565" Y="15.3473"/>
   <City X="35.764" Y="13.8018"/>
   <City X="20.945" Y="35.0761"/>
   <City X="3.4553" Y="0.48769"/>
   <City X="19.5395" Y="19.4599"/>
   <City X="5.8337" Y="18.6639"/>
   <City X="14.3288" Y="6.2384"/>
   <City X="14.0283" Y="39.3119"/>
   <City X="34.5043" Y="18.3162"/>
   <City X="29.9324" Y="30.2589"/>
   <City X="34.5004" Y="20.1222"/>
   <City X="24.2442" Y="34.2146"/>
   <City X="31.2653" Y="20.9339"/>
   <City X="26.79" Y="39.9188"/>
   <City X="39.1714" Y="25.3254"/>
   <City X="14.6095" Y="32.5052"/>
   <City X="15.843" Y="0.99092"/>
   <City X="1.4243" Y="39.1927"/>
   <City X="28.0777" Y="16.5528"/>
   <City X="26.2749" Y="26.217"/>
   <City X="33.7639" Y="31.2634"/>
   <City X="27.3846" Y="28.8205"/>
   <City X="23.4444" Y="32.8198"/>
   <City X="10.1267" Y="33.0083"/>
   <City X="32.6189" Y="6.6021"/>
   <City X="6.168" Y="34.3421"/>
   <City X="37.6439" Y="9.3781"/>
   <City X="36.0034" Y="19.9861"/>
   <City X="19.8912" Y="36.3011"/>
   <City X="27.2032" Y="28.9581"/>
   <City X="31.9595" Y="16.1704"/>
   <City X="35.3558" Y="1.6096"/>
   <City X="15.6896" Y="5.5451"/>
   <City X="8.6437" Y="23.5684"/>
</CityList>