<?xml version="1.0" encoding="utf-8"?>
<CityList>
   <City X="27.4784" Y="29.4025"/>
   <City X="11.8956" Y="36.6889"/>
   <City X="17.4903" Y="3.8088"/>
   <City X="7.7966" Y="7.515"/>
   <City X="11.8482" Y="10.8149"/>
   <City X="21.9139" Y="12.2225"/>
   <City X="8.2662" Y="11.0726"/>
   <City X="29.6813" Y="38.1832"/>
   <City X="37.3607" Y="5.3143"/>
   <City X="22.9303" Y="7.8875"/>
   <City X="6.366" Y="12.1847"/>
   <City X="17.5465" Y="30.7915"/>
   <City X="1.0784" Y="5.6853"/>
   <City X="0.011607" Y="35.7562"/>
   <City X="34.3498" Y="22.4555"/>
   <City X="7.1324" Y="18.0315"/>
   <City X="6.8082" Y="21.7512"/>
   <City X="21.7332" Y="11.5735"/>
   <City X="29.4335" Y="18.9913"/>
   <City X="24.6533" Y="14.4761"/>
   <City X="21.8964" Y="9.8128"/>
   <City X="24.8974" Y="27.9843"/>
   <City X="5.6898" Y="36.8243"/>
   <City X="29.5514" Y="31.4374"/>
   <City X="0.098924" Y="25.6168"/>
   <City X="34.5456" Y="30.8161"/>
   <City X="24.404" Y="24.5572"/>
   <City X="12.2887" Y="19.5911"/>
   <City X="25.3576" Y="38.9677"/>
   <City X="33.7491" Y="15.6832"/>
   <City X="29.2178" Y="8.1515"/>
   <City X="17.0303" Y="3.0706"/>
   <City X="4.6499" Y="33.1459"/>
   <City X="21.3454" Y="12.7955"/>
   <City X="27.4167" Y="30.0404"/>
   <City X="25.3004" Y="22.3419"/>
   <City X="2.0406" Y="37.4277"/>
   <City X="21.8286" Y="9.4458"/>
   <City X="4.2416" Y="6.8657"/>
   <City X="16.4225" Y="8.7727"/>
   <City X="24.0936" Y="6.8207"/>
   <City X="22.3988" Y="10.874"/>
   <City X="28.2452" Y="20.3795"/>
   <City X="3.5503" Y="11.4533"/>
   <City X="6.1686" Y="17.5412"/>
</CityList>